rdp_rust-0.5.3.dist-info/METADATA
rdp_rust-0.5.3.dist-info/WHEEL
rdp_rust/__init__.py
rdp_rust/rdp_rust.abi3.so
rdp_rust-0.5.3.dist-info/RECORD
