Metadata-Version: 2.1
Name: rdp-rust
Version: 0.5.3
Classifier: Development Status :: 4 - Beta
Classifier: Intended Audience :: Developers
Classifier: License :: OSI Approved :: MIT License
Classifier: Programming Language :: Python
Classifier: Programming Language :: Python :: 3
Classifier: Programming Language :: Python :: 3.7
Classifier: Programming Language :: Python :: 3.8
Classifier: Programming Language :: Python :: 3.9
Classifier: Programming Language :: Python :: 3.10
Requires-Dist: numpy>=1.16.0
Author: erik.langenborg@gmail.com
Author-email: erik.langenborg@gmail.com
License: MIT
Requires-Python: >=3.6
